smoltext/__init__.py
smoltext/__main__.py
smoltext/console_script.py
smoltext/fonts/__init__.py
smoltext/fonts/bold.py
smoltext/fonts/demonic.py
smoltext/fonts/emoji.py
smoltext/fonts/fancy.py
smoltext/fonts/handwriting.py
smoltext/fonts/italic.py
smoltext/fonts/monospace.py
smoltext/fonts/smallcaps.py
smoltext/fonts/subscript.py
smoltext-1.4.8.dist-info/LICENSE
smoltext-1.4.8.dist-info/METADATA
smoltext-1.4.8.dist-info/WHEEL
smoltext-1.4.8.dist-info/entry_points.txt
smoltext-1.4.8.dist-info/top_level.txt
smoltext-1.4.8.dist-info/RECORD
