Metadata-Version: 2.1
Name: smoltext
Version: 1.4.8
Summary: A font converter utility with the extra fonts included in utf8.
Home-page: UNKNOWN
Author: Sofi
License: MIT
Platform: UNKNOWN
Classifier: Programming Language :: Python :: 3
Classifier: License :: OSI Approved :: MIT License
Classifier: Operating System :: OS Independent
Requires-Python: >=3.6
